{
	"post": [
		{
			"thumbnail": "https://picsum.photos/400/200?random=1",
			"category": "Data Engineering",
			"title": "The Hidden Data Engine Behind Every Great Real Estate Map – What Brokers, Developers, and Investors Need to Know",
			"author": "patrick sang",
			"date": "2026-05-23",
			"excerpt": "You’ve used GIS to find parcels, check flood zones, or run a drive‑time analysis. The map looks simple – colourful polygons, a search bar, maybe a slider for school ratings. But behind that map is a machine of data engineering that determines whether your information is accurate, up‑to‑date, and fast enough for live use.\n\nIn 20 years of real estate tech, I’ve seen the same failures: a map that shows last year’s parcel boundaries, a query that takes 30 seconds to return comps, or a flood overlay that is misaligned by 50 metres. All those problems are data engineering problems, not GIS software problems. Here’s what you need to understand.\n\n1. Parcel Geometry Is Never “Perfect” – And That’s an Engineering Challenge\nCounties usually publish parcel data as Shapefiles or GeoPackages. But those files often contain invalid polygons: self‑intersecting boundaries, tiny slivers (area <0.001 m²), or missing rings. When raw data is loaded directly into a map, those errors can cause:\n\nDisappearing parcels (the renderer skips them)\n\nWrong area calculations (a sliver makes area 0.01 acres instead of 2 acres)\n\nFailed spatial joins (parcel won’t intersect its own flood zone because geometry is broken)\n\nData engineers run geometry validation and cleaning as the first step in the pipeline. Using libraries like shapely or PostGIS ST_MakeValid(), they fix the violations before any analysis. A good pipeline logs invalid geometries and alerts the operator – often indicating a title survey problem that needs human review.\n\nWhat you should ask your GIS vendor: “Do you run geometry validation on all parcels? What percentage are automatically fixed, and how are exceptions handled?”\n\n2. Coordinate Systems – The Silent Killer of Map Overlays\nA flood map from FEMA uses WGS84 (EPSG:4326) – latitude/longitude. County parcels often come in State Plane (e.g., EPSG:26986 for Massachusetts). If you simply overlay them without reprojection, parcels will appear shifted by hundreds of metres – sometimes in the wrong water body.\n\nThe engineering solution is automatic CRS transformation on every ingest. A good data pipeline:\n\nReads the source CRS from the file (if missing, asks user or assumes a default)\n\nTransforms all geometries to a uniform analysis CRS (often a projected coordinate system that preserves area, like State Plane)\n\nStores the original CRS as metadata for audit\n\nFor web maps, the final step transforms to Web Mercator (EPSG:3857), which is what Leaflet, Mapbox, and Google Maps use. That transformation happens inside the database or tile server – invisible to you.\n\nRed flag: If you ever see a real‑estate map where parcels and satellite imagery don’t line up, the CRS transformation was omitted or done incorrectly.\n\n3. Why “Find Similar Sales” Takes 0.3 Seconds (or 30 Seconds)\nThe operation “find all parcels sold in last 6 months within 500 metres of this parcel” is a distance join. Without a spatial index, the database must compare every pair of parcels – O(n²) complexity. For a county with 500,000 parcels, that’s 250 billion comparisons – impossible in real time.\n\nData engineers build spatial indexes (R‑trees, GiST indexes in PostGIS). An R‑tree organises geometries into nested bounding boxes, allowing the database to quickly discard far‑away parcels. The same query goes from 30 seconds to 0.3 seconds.\n\nBut there’s more: they also denormalise common queries. For example, if every user asks for “parcel + school district + flood zone”, they might create a materialised view that pre‑joins those layers nightly. The dashboard then reads that flat table – even faster.\n\nAsk your platform provider: “Do you use spatial indexes? Do you pre‑join common layers for performance?”\n\n4. The Nightly Parcel Update – Why Fresh Data Is Hard\nCounties update parcel boundaries and APN tables on different schedules: daily, weekly, or monthly. The naive approach is to delete all data and reload – but that’s slow (hours) and wasteful.\n\nData engineers use Change Data Capture (CDC). They compute a hash (fingerprint) of each parcel’s geometry + attributes. When a new county export arrives, they compare hashes:\n\nHash unchanged → ignore\n\nHash changed → update existing record\n\nNew APN appears → insert\n\nAPN missing (deleted parcel) → soft‑delete or archive\n\nThis reduces the processing window from hours to minutes and ensures that the map doesn’t blink (no full teardown). It also allows a history table – you can see what the parcel looked like last month, which is essential for tax appeals and litigation.\n\n5. Vector Tiles: The Secret to a Snappy Web Map\nOld‑style web maps use raster tiles – the server draws a PNG image for every zoom level. If you have 20 layers (parcels, zoning, easements, comps, etc.), the server must render those images on‑the‑fly, which is slow and rigid.\n\nModern real‑estate dashboards use vector tiles (MVT) . A data engineer pre‑processes all layers into small, compact tiles containing the raw geometry and attributes (but simplified). The user’s browser downloads those tiles and renders them instantly. You can change the styling (e.g., colour parcels by school rating) without asking the server for new images.\n\nThe engineering challenge is tile generation – simplifying geometries so tiles aren’t huge but still look sharp. Tools like Tippecanoe or PostGIS’s ST_AsMVT() are used to create tile pyramids that are then served via a CDN.\n\nResult: A map with millions of parcels that pans and zooms as smoothly as Google Maps.\n\nBottom Line for Real Estate Pros\nThe map is just the tip of the iceberg. Underneath is a stack of geometry validation, CRS transformation, spatial indexing, CDC pipelines, and vector tiles. When you evaluate a real‑estate GIS product or build your own, invest in data engineering early. It’s the difference between “that map is cool” and “I trust this data for a $10M decision.”\n\n"
		},
		{
			"thumbnail": "https://picsum.photos/800/400?random=1"
		}
	]
}